setup.py
matrix_algebra11/__init__.py
matrix_algebra11/python_code.py
matrix_algebra11.egg-info/PKG-INFO
matrix_algebra11.egg-info/SOURCES.txt
matrix_algebra11.egg-info/dependency_links.txt
matrix_algebra11.egg-info/not-zip-safe
matrix_algebra11.egg-info/top_level.txt