Metadata-Version: 1.0
Name: matrix-algebra11
Version: 0.1.1
Summary: basic matrix algebra
Home-page: UNKNOWN
Author: UNKNOWN
Author-email: UNKNOWN
License: UNKNOWN
Platform: UNKNOWN
